{
  "id": "4fb76952-af32-4d09-85c8-85e7f1265774",
  "prevId": "8c9ea751-7eea-48ac-8563-8d43a1e5725f",
  "version": "7",
  "dialect": "postgresql",
  "tables": {
    "public.admins": {
      "name": "admins",
      "schema": "",
      "columns": {
        "discord_user_id": {
          "name": "discord_user_id",
          "type": "varchar",
          "primaryKey": true,
          "notNull": true
        },
        "otp": {
          "name": "otp",
          "type": "varchar",
          "primaryKey": false,
          "notNull": true
        },
        "is_admin": {
          "name": "is_admin",
          "type": "boolean",
          "primaryKey": false,
          "notNull": true,
          "default": false
        },
        "created_at": {
          "name": "created_at",
          "type": "timestamp",
          "primaryKey": false,
          "notNull": true,
          "default": "now()"
        }
      },
      "indexes": {},
      "foreignKeys": {},
      "compositePrimaryKeys": {},
      "uniqueConstraints": {}
    },
    "public.media_items": {
      "name": "media_items",
      "schema": "",
      "columns": {
        "id": {
          "name": "id",
          "type": "varchar",
          "primaryKey": true,
          "notNull": true
        },
        "manager_id": {
          "name": "manager_id",
          "type": "integer",
          "primaryKey": false,
          "notNull": true
        },
        "manager_type": {
          "name": "manager_type",
          "type": "manager_type",
          "typeSchema": "public",
          "primaryKey": false,
          "notNull": true
        },
        "manager_config_id": {
          "name": "manager_config_id",
          "type": "varchar",
          "primaryKey": false,
          "notNull": true
        },
        "title": {
          "name": "title",
          "type": "varchar",
          "primaryKey": false,
          "notNull": true
        },
        "size_on_disk": {
          "name": "size_on_disk",
          "type": "numeric",
          "primaryKey": false,
          "notNull": true,
          "default": "'0'"
        },
        "release_date": {
          "name": "release_date",
          "type": "timestamp",
          "primaryKey": false,
          "notNull": true
        },
        "year": {
          "name": "year",
          "type": "integer",
          "primaryKey": false,
          "notNull": false
        },
        "has_file": {
          "name": "has_file",
          "type": "boolean",
          "primaryKey": false,
          "notNull": false,
          "default": false
        },
        "imdb_id": {
          "name": "imdb_id",
          "type": "varchar",
          "primaryKey": false,
          "notNull": false
        },
        "tmdb_id": {
          "name": "tmdb_id",
          "type": "integer",
          "primaryKey": false,
          "notNull": false
        },
        "rating": {
          "name": "rating",
          "type": "real",
          "primaryKey": false,
          "notNull": false
        },
        "added_to_manager": {
          "name": "added_to_manager",
          "type": "timestamp",
          "primaryKey": false,
          "notNull": true
        },
        "path_on_disk": {
          "name": "path_on_disk",
          "type": "varchar",
          "primaryKey": false,
          "notNull": false
        },
        "image": {
          "name": "image",
          "type": "varchar",
          "primaryKey": false,
          "notNull": false
        },
        "created_at": {
          "name": "created_at",
          "type": "timestamp",
          "primaryKey": false,
          "notNull": true,
          "default": "now()"
        },
        "updated_at": {
          "name": "updated_at",
          "type": "timestamp",
          "primaryKey": false,
          "notNull": false,
          "default": "now()"
        }
      },
      "indexes": {
        "manager_id_idx": {
          "name": "manager_id_idx",
          "columns": [
            {
              "expression": "manager_id",
              "isExpression": false,
              "asc": true,
              "nulls": "last"
            }
          ],
          "isUnique": false,
          "concurrently": false,
          "method": "btree",
          "with": {}
        },
        "manager_type_idx": {
          "name": "manager_type_idx",
          "columns": [
            {
              "expression": "manager_type",
              "isExpression": false,
              "asc": true,
              "nulls": "last"
            }
          ],
          "isUnique": false,
          "concurrently": false,
          "method": "btree",
          "with": {}
        },
        "manager_config_id_idx": {
          "name": "manager_config_id_idx",
          "columns": [
            {
              "expression": "manager_config_id",
              "isExpression": false,
              "asc": true,
              "nulls": "last"
            }
          ],
          "isUnique": false,
          "concurrently": false,
          "method": "btree",
          "with": {}
        },
        "added_to_manager_idx": {
          "name": "added_to_manager_idx",
          "columns": [
            {
              "expression": "added_to_manager",
              "isExpression": false,
              "asc": true,
              "nulls": "last"
            }
          ],
          "isUnique": false,
          "concurrently": false,
          "method": "btree",
          "with": {}
        }
      },
      "foreignKeys": {},
      "compositePrimaryKeys": {},
      "uniqueConstraints": {
        "media_items_manager_id_manager_config_id_unique": {
          "name": "media_items_manager_id_manager_config_id_unique",
          "nullsNotDistinct": false,
          "columns": [
            "manager_id",
            "manager_config_id"
          ]
        }
      }
    },
    "public.subscribers": {
      "name": "subscribers",
      "schema": "",
      "columns": {
        "discord_user_id": {
          "name": "discord_user_id",
          "type": "varchar",
          "primaryKey": true,
          "notNull": true
        },
        "created_at": {
          "name": "created_at",
          "type": "timestamp",
          "primaryKey": false,
          "notNull": true,
          "default": "now()"
        }
      },
      "indexes": {},
      "foreignKeys": {},
      "compositePrimaryKeys": {},
      "uniqueConstraints": {}
    },
    "public.items_to_delete": {
      "name": "items_to_delete",
      "schema": "",
      "columns": {
        "id": {
          "name": "id",
          "type": "varchar",
          "primaryKey": true,
          "notNull": true
        },
        "delete_after": {
          "name": "delete_after",
          "type": "timestamp",
          "primaryKey": false,
          "notNull": true
        },
        "deleted_at": {
          "name": "deleted_at",
          "type": "timestamp",
          "primaryKey": false,
          "notNull": false
        },
        "created_at": {
          "name": "created_at",
          "type": "timestamp",
          "primaryKey": false,
          "notNull": true,
          "default": "now()"
        }
      },
      "indexes": {},
      "foreignKeys": {
        "items_to_delete_id_media_items_id_fk": {
          "name": "items_to_delete_id_media_items_id_fk",
          "tableFrom": "items_to_delete",
          "tableTo": "media_items",
          "columnsFrom": [
            "id"
          ],
          "columnsTo": [
            "id"
          ],
          "onDelete": "cascade",
          "onUpdate": "no action"
        }
      },
      "compositePrimaryKeys": {},
      "uniqueConstraints": {}
    },
    "public.voting_sessions": {
      "name": "voting_sessions",
      "schema": "",
      "columns": {
        "id": {
          "name": "id",
          "type": "varchar",
          "primaryKey": true,
          "notNull": true
        },
        "discord_message_id": {
          "name": "discord_message_id",
          "type": "varchar",
          "primaryKey": false,
          "notNull": true
        },
        "created_at": {
          "name": "created_at",
          "type": "timestamp",
          "primaryKey": false,
          "notNull": true,
          "default": "now()"
        },
        "ends_at": {
          "name": "ends_at",
          "type": "timestamp",
          "primaryKey": false,
          "notNull": true
        },
        "handled": {
          "name": "handled",
          "type": "boolean",
          "primaryKey": false,
          "notNull": true,
          "default": false
        },
        "vote_outcome": {
          "name": "vote_outcome",
          "type": "vote_outcome",
          "typeSchema": "public",
          "primaryKey": false,
          "notNull": false
        }
      },
      "indexes": {
        "discord_message_id_idx": {
          "name": "discord_message_id_idx",
          "columns": [
            {
              "expression": "discord_message_id",
              "isExpression": false,
              "asc": true,
              "nulls": "last"
            }
          ],
          "isUnique": false,
          "concurrently": false,
          "method": "btree",
          "with": {}
        },
        "handled_idx": {
          "name": "handled_idx",
          "columns": [
            {
              "expression": "handled",
              "isExpression": false,
              "asc": true,
              "nulls": "last"
            }
          ],
          "isUnique": false,
          "concurrently": false,
          "method": "btree",
          "with": {}
        }
      },
      "foreignKeys": {
        "voting_sessions_id_media_items_id_fk": {
          "name": "voting_sessions_id_media_items_id_fk",
          "tableFrom": "voting_sessions",
          "tableTo": "media_items",
          "columnsFrom": [
            "id"
          ],
          "columnsTo": [
            "id"
          ],
          "onDelete": "cascade",
          "onUpdate": "no action"
        }
      },
      "compositePrimaryKeys": {},
      "uniqueConstraints": {}
    },
    "public.whitelist": {
      "name": "whitelist",
      "schema": "",
      "columns": {
        "id": {
          "name": "id",
          "type": "varchar",
          "primaryKey": true,
          "notNull": true
        },
        "created_at": {
          "name": "created_at",
          "type": "timestamp",
          "primaryKey": false,
          "notNull": true,
          "default": "now()"
        }
      },
      "indexes": {},
      "foreignKeys": {
        "whitelist_id_media_items_id_fk": {
          "name": "whitelist_id_media_items_id_fk",
          "tableFrom": "whitelist",
          "tableTo": "media_items",
          "columnsFrom": [
            "id"
          ],
          "columnsTo": [
            "id"
          ],
          "onDelete": "cascade",
          "onUpdate": "no action"
        }
      },
      "compositePrimaryKeys": {},
      "uniqueConstraints": {}
    }
  },
  "enums": {
    "public.manager_type": {
      "name": "manager_type",
      "schema": "public",
      "values": [
        "radarr",
        "sonarr"
      ]
    },
    "public.vote_outcome": {
      "name": "vote_outcome",
      "schema": "public",
      "values": [
        "keep",
        "delete"
      ]
    }
  },
  "schemas": {},
  "sequences": {},
  "_meta": {
    "columns": {},
    "schemas": {},
    "tables": {}
  }
}